lspy/__init__.py
lspy/main.py
lspy/assets/favicon.ico
lspy/assets/index.html
lspy/assets/main.min.js
lspy/src/LIVE_exec_py3.py
lspy/src/__init__.py
lspy/src/bot.py
lspy/src/generate_json_trace.py
lspy/src/pg_encoder.py
lspy/src/pg_logger.py
lspy/src/viz_interaction.py
tests/__init__.py
tests/main.py
lspy-0.0.4.dist-info/LICENSE
lspy-0.0.4.dist-info/METADATA
lspy-0.0.4.dist-info/WHEEL
lspy-0.0.4.dist-info/entry_points.txt
lspy-0.0.4.dist-info/top_level.txt
lspy-0.0.4.dist-info/zip-safe
lspy-0.0.4.dist-info/RECORD
